[{"Name": "McGlovin ( \u00b0\u25a1\u00b0) \ufe35", "Rank": 11708, "Rating": 1.28, "KpD": 1.19, "ADR": 91, "Games": 15, "Win_Rate": 40, "Entry_Attempts": 19, "Worst_Match": 0.6, "Best_Match": 2.04, "Kills": 267, "Deaths": 225, "Assists": 62, "Kill_Shot_Ratio": 4.09, "Avatar": "https://avatars.steamstatic.com/f4f20b712c180e79c42861ff69463229cabee40d_full.jpg", "Maps": {"de_ancient": 2, "de_anubis": 1, "de_inferno": 4, "de_mirage": 1, "de_nuke": 3, "de_overpass": 1, "de_vertigo": 3}, "1v1": 2, "1v2": 0, "1v3": 0, "1v4": 0, "1v5": 0, "3k": 16, "4k": 4, "5k": 3}, {"Name": "The Diddler", "Rank": 10985, "Rating": 0.88, "KpD": 0.73, "ADR": 69, "Games": 20, "Win_Rate": 35, "Entry_Attempts": 19, "Worst_Match": 0.24, "Best_Match": 1.44, "Kills": 220, "Deaths": 303, "Assists": 108, "Kill_Shot_Ratio": 3.83, "Avatar": "https://avatars.steamstatic.com/77fb2cccd8999b58a453538e4eab1654b0d70225_full.jpg", "Maps": {"de_ancient": 4, "de_inferno": 5, "de_mirage": 2, "de_nuke": 2, "de_overpass": 1, "de_vertigo": 6}, "1v1": 1, "1v2": 0, "1v3": 0, "1v4": 0, "1v5": 0, "3k": 7, "4k": 0, "5k": 0}, {"Name": "BagRa", "Rank": 11586, "Rating": 1.07, "KpD": 0.91, "ADR": 76, "Games": 11, "Win_Rate": 27, "Entry_Attempts": 18, "Worst_Match": 0.57, "Best_Match": 1.54, "Kills": 135, "Deaths": 149, "Assists": 53, "Kill_Shot_Ratio": 3.1, "Avatar": "https://avatars.steamstatic.com/2840515f9fe13f04a607629ecef2df101e4af4a1_full.jpg", "Maps": {"de_ancient": 3, "de_inferno": 2, "de_mirage": 2, "de_nuke": 1, "de_overpass": 2, "de_vertigo": 1}, "1v1": 2, "1v2": 1, "1v3": 0, "1v4": 0, "1v5": 0, "3k": 5, "4k": 1, "5k": 1}, {"Name": "whizz", "Rank": 14772, "Rating": 1.42, "KpD": 1.4, "ADR": 95, "Games": 5, "Win_Rate": 60, "Entry_Attempts": 30, "Worst_Match": 0.71, "Best_Match": 2.29, "Kills": 77, "Deaths": 55, "Assists": 19, "Kill_Shot_Ratio": 8.44, "Avatar": "https://avatars.steamstatic.com/d60ff0a7b378c3f4d3311fd2325ebe4308645856_full.jpg", "Maps": {"de_ancient": 1, "de_mirage": 1, "de_nuke": 1, "de_overpass": 1, "de_vertigo": 1}, "1v1": 2, "1v2": 1, "1v3": 0, "1v4": 0, "1v5": 0, "3k": 4, "4k": 1, "5k": 0}, {"Name": "devii", "Rank": 12056, "Rating": 1.2, "KpD": 1.04, "ADR": 91, "Games": 13, "Win_Rate": 31, "Entry_Attempts": 16, "Worst_Match": 0.46, "Best_Match": 1.65, "Kills": 207, "Deaths": 200, "Assists": 67, "Kill_Shot_Ratio": 4.6, "Avatar": "https://avatars.steamstatic.com/40093d2f97288a55cfae7210c39b8a6fdfb24e6b_full.jpg", "Maps": {"de_ancient": 2, "de_inferno": 4, "de_mirage": 2, "de_nuke": 1, "de_vertigo": 4}, "1v1": 6, "1v2": 0, "1v3": 1, "1v4": 0, "1v5": 0, "3k": 11, "4k": 4, "5k": 0}, {"Name": "nickh", "Rank": 10585, "Rating": 1.04, "KpD": 0.95, "ADR": 78, "Games": 14, "Win_Rate": 21, "Entry_Attempts": 22, "Worst_Match": 0.38, "Best_Match": 1.55, "Kills": 207, "Deaths": 219, "Assists": 51, "Kill_Shot_Ratio": 5.86, "Avatar": "https://avatars.steamstatic.com/506c50fb505ab7d0158720a876ca74a39cf66c94_full.jpg", "Maps": {"de_ancient": 2, "de_anubis": 1, "de_inferno": 4, "de_mirage": 2, "de_nuke": 1, "de_overpass": 1, "de_vertigo": 3}, "1v1": 1, "1v2": 3, "1v3": 0, "1v4": 0, "1v5": 0, "3k": 12, "4k": 4, "5k": 0}, {"Name": "vahto", "Rank": 10795, "Rating": 0.68, "KpD": 0.48, "ADR": 56, "Games": 6, "Win_Rate": 17, "Entry_Attempts": 21, "Worst_Match": 0.47, "Best_Match": 0.93, "Kills": 48, "Deaths": 99, "Assists": 34, "Kill_Shot_Ratio": 3.1, "Avatar": "https://avatars.steamstatic.com/0542338c943d7fb3f0329cac94d7809331101748_full.jpg", "Maps": {"de_ancient": 1, "de_anubis": 1, "de_inferno": 2, "de_vertigo": 2}, "1v1": 1, "1v2": 1, "1v3": 0, "1v4": 0, "1v5": 0, "3k": 1, "4k": 0, "5k": 0}, {"Name": "Hoodrat", "Rank": 10927, "Rating": 1.15, "KpD": 1.04, "ADR": 83, "Games": 15, "Win_Rate": 33, "Entry_Attempts": 29, "Worst_Match": 0.49, "Best_Match": 2.37, "Kills": 243, "Deaths": 234, "Assists": 58, "Kill_Shot_Ratio": 6.23, "Avatar": "https://avatars.steamstatic.com/0087c2b7931a6cf83af8bd85e7887127986912ca_full.jpg", "Maps": {"de_ancient": 2, "de_anubis": 1, "de_inferno": 4, "de_mirage": 1, "de_nuke": 2, "de_overpass": 1, "de_vertigo": 4}, "1v1": 4, "1v2": 2, "1v3": 0, "1v4": 0, "1v5": 0, "3k": 17, "4k": 5, "5k": 0}, {"Name": "DuttyFusion", "Rank": 15508, "Rating": 0, "KpD": 0, "ADR": 0, "Games": 0, "Win_Rate": 0, "Entry_Attempts": 0, "Worst_Match": 0.0, "Best_Match": 0.0, "Kills": 0, "Deaths": 0, "Assists": 0, "Kill_Shot_Ratio": 0.0, "Avatar": "https://avatars.steamstatic.com/9e98f7c9b0a73a5a5804d8acc34496a451b2c434_full.jpg", "Maps": {}, "1v1": 0, "1v2": 0, "1v3": 0, "1v4": 0, "1v5": 0, "3k": 0, "4k": 0, "5k": 0}, {"Name": "Logan Ninefingers", "Rank": 10000, "Rating": 0.68, "KpD": 0.57, "ADR": 51, "Games": 18, "Win_Rate": 28, "Entry_Attempts": 12, "Worst_Match": 0.39, "Best_Match": 1.13, "Kills": 159, "Deaths": 279, "Assists": 71, "Kill_Shot_Ratio": 4.1, "Avatar": "https://avatars.steamstatic.com/dc3c4f56d9811a193ab54c89e055c47ebccee6eb_full.jpg", "Maps": {"de_ancient": 4, "de_anubis": 1, "de_inferno": 5, "de_mirage": 2, "de_nuke": 2, "de_overpass": 1, "de_vertigo": 3}, "1v1": 3, "1v2": 1, "1v3": 0, "1v4": 0, "1v5": 0, "3k": 2, "4k": 0, "5k": 0}, {"Name": "Andy", "Rank": 13891, "Rating": 1.48, "KpD": 1.6, "ADR": 100, "Games": 7, "Win_Rate": 57, "Entry_Attempts": 22, "Worst_Match": 0.46, "Best_Match": 1.91, "Kills": 134, "Deaths": 84, "Assists": 18, "Kill_Shot_Ratio": 7.23, "Avatar": "https://avatars.steamstatic.com/9fb905748f3360cd31bbd32e36cd01a31cd1f32a_full.jpg", "Maps": {"de_ancient": 1, "de_inferno": 1, "de_mirage": 1, "de_nuke": 1, "de_overpass": 1, "de_vertigo": 2}, "1v1": 3, "1v2": 1, "1v3": 0, "1v4": 0, "1v5": 0, "3k": 9, "4k": 2, "5k": 1}, {"Name": "aWoL", "Rank": 11429, "Rating": 0, "KpD": 0, "ADR": 0, "Games": 0, "Win_Rate": 0, "Entry_Attempts": 0, "Worst_Match": 0.0, "Best_Match": 0.0, "Kills": 0, "Deaths": 0, "Assists": 0, "Kill_Shot_Ratio": 0.0, "Avatar": "https://avatars.steamstatic.com/ca9f5275ecaf42d23d5fae19deb7aa7fa5bc9662_full.jpg", "Maps": {}, "1v1": 0, "1v2": 0, "1v3": 0, "1v4": 0, "1v5": 0, "3k": 0, "4k": 0, "5k": 0}, {"Name": "Astro", "Rank": 0, "Rating": 1.15, "KpD": 0.97, "ADR": 95, "Games": 2, "Win_Rate": 0, "Entry_Attempts": 25, "Worst_Match": 1.05, "Best_Match": 1.25, "Kills": 32, "Deaths": 33, "Assists": 6, "Kill_Shot_Ratio": 4.28, "Avatar": "https://avatars.steamstatic.com/1c0b5c37a442a2d39f32902ec42f2e26ba6a142e_full.jpg", "Maps": {"de_inferno": 1, "de_vertigo": 1}, "1v1": 1, "1v2": 0, "1v3": 0, "1v4": 0, "1v5": 0, "3k": 0, "4k": 1, "5k": 0}, {"Name": "Snizzle", "Rank": 11427, "Rating": 1.05, "KpD": 0.91, "ADR": 79, "Games": 9, "Win_Rate": 44, "Entry_Attempts": 21, "Worst_Match": 0.58, "Best_Match": 1.33, "Kills": 115, "Deaths": 127, "Assists": 53, "Kill_Shot_Ratio": 4.09, "Avatar": "https://avatars.steamstatic.com/6330c0531c83e7262767b52a29728f6801bcc289_full.jpg", "Maps": {"de_ancient": 3, "de_inferno": 3, "de_mirage": 1, "de_nuke": 1, "de_overpass": 1}, "1v1": 2, "1v2": 1, "1v3": 0, "1v4": 0, "1v5": 0, "3k": 5, "4k": 1, "5k": 0}]